studenttask/README.rst
studenttask/pyproject.toml
studenttask/studenttask/__init__.py
studenttask/tests/__init__.py
studenttask/tests/test_studenttask.py
studenttask-0.1.0.dist-info/WHEEL
studenttask-0.1.0.dist-info/METADATA
studenttask-0.1.0.dist-info/RECORD
