Metadata-Version: 2.1
Name: studenttask
Version: 0.1.0
Summary: Data Challenge
Author: Takehiro Tsurumi
Author-email: cranelook87@gmail.com
Requires-Python: >=3.9,<4.0
Classifier: Programming Language :: Python :: 3
Classifier: Programming Language :: Python :: 3.10
Classifier: Programming Language :: Python :: 3.9
Requires-Dist: pendulum (>=2.1.2,<3.0.0)
